LICENSE
MANIFEST.in
setup.cfg
setup.py
testutils/__init__.py
testutils.egg-info/PKG-INFO
testutils.egg-info/SOURCES.txt
testutils.egg-info/dependency_links.txt
testutils.egg-info/top_level.txt